lencode/__init__.py
lencode/api.py
lencode-0.1.2.dist-info/LICENSE
lencode-0.1.2.dist-info/METADATA
lencode-0.1.2.dist-info/WHEEL
lencode-0.1.2.dist-info/top_level.txt
lencode-0.1.2.dist-info/RECORD
