Metadata-Version: 2.1
Name: lencode
Version: 0.1.2
Summary: 编码/加密工具包 Encoding/Encryption Toolkit
Home-page: https://github.com/linupychiang/lencode
Author: linupy
Author-email: linupy@163.com
License: UNKNOWN
Platform: UNKNOWN
Classifier: Programming Language :: Python :: 3
Classifier: License :: OSI Approved :: MIT License
Classifier: Operating System :: OS Independent
Requires-Python: >=3
License-File: LICENSE
